[
    {
        "instrumentcode": 8573,
        "buy": 0.65,
        "sell": 0.2,
        "rank": 1,
        "currency": "JPY"
    },
    {
        "instrumentcode": 8978,
        "buy": 0.65,
        "sell": 0.18,
        "rank": 2,
        "currency": "JPY"
    },
    {
        "instrumentcode": 8540,
        "buy": 0.65,
        "sell": 0.18,
        "rank": 3,
        "currency": "JPY"
    },
    {
        "instrumentcode": 8225,
        "buy": 0.65,
        "sell": 0.18,
        "rank": 4,
        "currency": "JPY"
    },
    {
        "instrumentcode": 8828,
        "buy": 0.65,
        "sell": 0.18,
        "rank": 5,
        "currency": "JPY"
    },
    {
        "instrumentcode": 8391,
        "buy": 0.65,
        "sell": 0.18,
        "rank": 6,
        "currency": "JPY"
    }
]